<?xml version="1.0" encoding="UTF-8"?>
<TaskOptions>
  <TaskOptions>
    <option name="arguments" value="$ProjectFileDir$/src --out-dir lib --source-maps --presets es2015" />
    <option name="checkSyntaxErrors" value="true" />
    <option name="description" />
    <option name="exitCodeBehavior" value="ERROR" />
    <option name="fileExtension" value="js" />
    <option name="immediateSync" value="true" />
    <option name="name" value="Babel:Bob" />
    <option name="output" value="lib/$FileNameWithoutExtension$.js:lib/$FileNameWithoutExtension$.js.map" />
    <option name="outputFilters">
      <array />
    </option>
    <option name="outputFromStdout" value="false" />
    <option name="program" value="/Users/if/dev/generator/node_modules/.bin/babel" />
    <option name="scopeName" value="Project Files" />
    <option name="trackOnlyRoot" value="false" />
    <option name="workingDir" value="$ContentRoot$" />
    <envs />
  </TaskOptions>
</TaskOptions>

